{
  "parent": "minecraft:recipes/root",
  "criteria": {
    "has_calcite_or_calcite_pavers": {
      "conditions": {
        "items": [
          {
            "items": [
              "minecraft:calcite",
              "stoneworks:calcite_pavers"
            ]
          }
        ]
      },
      "trigger": "minecraft:inventory_changed"
    },
    "has_the_recipe": {
      "conditions": {
        "recipe": "stoneworks:calcite_paver_wall_from_calcite_or_calcite_pavers_stonecutting"
      },
      "trigger": "minecraft:recipe_unlocked"
    }
  },
  "requirements": [
    [
      "has_the_recipe",
      "has_calcite_or_calcite_pavers"
    ]
  ],
  "rewards": {
    "recipes": [
      "stoneworks:calcite_paver_wall_from_calcite_or_calcite_pavers_stonecutting"
    ]
  }
}