{
  "parent": "minecraft:recipes/root",
  "criteria": {
    "has_the_recipe": {
      "conditions": {
        "recipe": "stoneworks:tuff_plate_wall_from_tuff_plates_stonecutting"
      },
      "trigger": "minecraft:recipe_unlocked"
    },
    "has_tuff_plates": {
      "conditions": {
        "items": [
          {
            "items": [
              "stoneworks:tuff_plates"
            ]
          }
        ]
      },
      "trigger": "minecraft:inventory_changed"
    }
  },
  "requirements": [
    [
      "has_the_recipe",
      "has_tuff_plates"
    ]
  ],
  "rewards": {
    "recipes": [
      "stoneworks:tuff_plate_wall_from_tuff_plates_stonecutting"
    ]
  }
}